.gitignore
.stickler.yml
.travis.yml
setup.py
tox.ini
.github/main.workflow
docs/README.md
examples/ch4.xyz
examples/ch4all-120762.pb
examples/client.py
examples/example.py
examples/exit.py
examples/force
examples/server.py
kconmd/__init__.py
kconmd.egg-info/PKG-INFO
kconmd.egg-info/SOURCES.txt
kconmd.egg-info/dependency_links.txt
kconmd.egg-info/requires.txt
kconmd.egg-info/top_level.txt
kconmd.egg-info/zip-safe
kconmd/force/__init__.py
kconmd/force/f_vdw.py
kconmd/force/feed.py
kconmd/kcnn/.gitignore
kconmd/kcnn/__init__.py
kconmd/kcnn/amsgrad.py
kconmd/kcnn/constants.py
kconmd/kcnn/inference.py
kconmd/kcnn/kcnn.py
kconmd/kcnn/pipeline.py
kconmd/kcnn/predictor.py
kconmd/kcnn/save_model.py
kconmd/kcnn/summary_utils.py
kconmd/kcnn/transformer.py
kconmd/kcnn/utils.py
kconmd/kconmd/__init__.py
kconmd/server/__init__.py
kconmd/test/__init__.py
kconmd/test/test.pb
kconmd/test/test.xyz
kconmd/test/test_kconmd.py