Metadata-Version: 2.1
Name: kconmd
Version: 1.0.17
Summary: Molecular dynamics (MD) simulations supported by k-Bags Convolutional Neural Network (kcon).
Home-page: https://github.com/njzjz/kconmd
Author: Jinzhe Zeng
Author-email: jzzeng@stu.ecnu.edu.cn
License: UNKNOWN
Keywords: molecular dynamics kcon
Platform: UNKNOWN
Classifier: Natural Language :: English
Classifier: Operating System :: POSIX :: Linux
Classifier: Operating System :: Microsoft :: Windows
Classifier: Programming Language :: Python :: 3.6
Classifier: Topic :: Scientific/Engineering :: Chemistry
Classifier: Topic :: Software Development :: Libraries :: Python Modules
Classifier: Topic :: Software Development :: Version Control :: Git
Requires-Python: ~=3.6.0
Provides-Extra: tf_gpu
Provides-Extra: test
Provides-Extra: tf
